LICENSE
MANIFEST.in
README.md
VERSION
setup.py
frida_potluck.egg-info/PKG-INFO
frida_potluck.egg-info/SOURCES.txt
frida_potluck.egg-info/dependency_links.txt
frida_potluck.egg-info/entry_points.txt
frida_potluck.egg-info/requires.txt
frida_potluck.egg-info/top_level.txt
potluck/__init__.py
potluck/__main__.py
potluck/agent.js
potluck/agent.py
potluck/constants.py
potluck/utils.py
potluck/commands/__init__.py
potluck/commands/memory.py
potluck/commands/process.py
potluck/commands/system.py
potluck/interfaces/__init__.py
potluck/interfaces/base.py
potluck/interfaces/process.py
potluck/interfaces/thread.py