Metadata-Version: 2.1
Name: frida-potluck
Version: 1.0.0
Summary: Custom debugger combining dynamic instrumentation with symbolic execution
Home-page: https://github.com/johneiser/potluck
Author: johneiser
License: gpl-3.0
Platform: UNKNOWN
Classifier: Development Status :: 3 - Alpha
Classifier: Programming Language :: Python :: 3
Classifier: Programming Language :: Python :: 3.5
Classifier: Programming Language :: Python :: 3.6
Classifier: Programming Language :: Python :: 3.7
Requires-Python: >=3.5.0
